LICENSE
MANIFEST.in
README.md
setup.py
impact/__init__.py
impact/artifact_ros.py
impact/diagram.py
impact/dotdict.py
impact/helpers.py
impact/mask.py
impact/model.py
impact/mpc.py
impact/+impact/DirectCollocation.m
impact/+impact/DotDict.m
impact/+impact/MPC.m
impact/+impact/Model.m
impact/+impact/MultipleShooting.m
impact/+impact/PythonCasadiInterface.m
impact/+impact/SingleShooting.m
impact/+impact/export_simulink_model.m
impact/+impact/external_method.m
impact/+impact/simulink_parse_states.m
impact/templates/python/impact.py
impact/templates/simulink/lib2016b.slx
impact_meco.egg-info/PKG-INFO
impact_meco.egg-info/SOURCES.txt
impact_meco.egg-info/dependency_links.txt
impact_meco.egg-info/requires.txt
impact_meco.egg-info/top_level.txt