Metadata-Version: 2.1
Name: impact-meco
Version: 0.6.1
Summary: DIRAC MPC
Home-page: https://gitlab.kuleuven.be/meco-software/impact
Download-URL: https://gitlab.kuleuven.be/meco-software/impact/-/archive/v0.6.1/impact-v0.6.1.tar.gz
Author: MECO-Group
Author-email: joris.gillis@kuleuven.be
License: LICENSE
License-File: LICENSE
